[
  {
    "name": "Mythic Seal #1",
    "description": "Unique NFT Mythical Seal for your Sunflower Land Farm. Made by Project Dignity.",
    "image": "https://raw.githubusercontent.com/tiffanydys/seals/main/preview/seal_preview.gif",
    "edition": 1,
    "date": 1659861041798,
    "founders": "Project Dignity: Tiffanydys, DonatasDee, VadimasVP, Paluras"
  },
  {
    "name": "Mythic Seal #2",
    "description": "Unique NFT Mythical Seal for your Sunflower Land Farm. Made by Project Dignity.",
    "image": "https://raw.githubusercontent.com/tiffanydys/seals/main/preview/seal_preview.gif",
    "edition": 2,
    "date": 1659861041798,
    "founders": "Project Dignity: Tiffanydys, DonatasDee, VadimasVP, Paluras"
  },
  {
    "name": "Mythic Seal #3",
    "description": "Unique NFT Mythical Seal for your Sunflower Land Farm. Made by Project Dignity.",
    "image": "https://raw.githubusercontent.com/tiffanydys/seals/main/preview/seal_preview.gif",
    "edition": 3,
    "date": 1659861041798,
    "founders": "Project Dignity: Tiffanydys, DonatasDee, VadimasVP, Paluras"
  },
  {
    "name": "Mythic Seal #4",
    "description": "Unique NFT Mythical Seal for your Sunflower Land Farm. Made by Project Dignity.",
    "image": "https://raw.githubusercontent.com/tiffanydys/seals/main/preview/seal_preview.gif",
    "edition": 4,
    "date": 1659861041798,
    "founders": "Project Dignity: Tiffanydys, DonatasDee, VadimasVP, Paluras"
  },
  {
    "name": "Mythic Seal #5",
    "description": "Unique NFT Mythical Seal for your Sunflower Land Farm. Made by Project Dignity.",
    "image": "https://raw.githubusercontent.com/tiffanydys/seals/main/preview/seal_preview.gif",
    "edition": 5,
    "date": 1659861041798,
    "founders": "Project Dignity: Tiffanydys, DonatasDee, VadimasVP, Paluras"
  },
  {
    "name": "Mythic Seal #6",
    "description": "Unique NFT Mythical Seal for your Sunflower Land Farm. Made by Project Dignity.",
    "image": "https://raw.githubusercontent.com/tiffanydys/seals/main/preview/seal_preview.gif",
    "edition": 6,
    "date": 1659861041798,
    "founders": "Project Dignity: Tiffanydys, DonatasDee, VadimasVP, Paluras"
  },
  {
    "name": "Mythic Seal #7",
    "description": "Unique NFT Mythical Seal for your Sunflower Land Farm. Made by Project Dignity.",
    "image": "https://raw.githubusercontent.com/tiffanydys/seals/main/preview/seal_preview.gif",
    "edition": 7,
    "date": 1659861041798,
    "founders": "Project Dignity: Tiffanydys, DonatasDee, VadimasVP, Paluras"
  },
  {
    "name": "Mythic Seal #8",
    "description": "Unique NFT Mythical Seal for your Sunflower Land Farm. Made by Project Dignity.",
    "image": "https://raw.githubusercontent.com/tiffanydys/seals/main/preview/seal_preview.gif",
    "edition": 8,
    "date": 1659861041798,
    "founders": "Project Dignity: Tiffanydys, DonatasDee, VadimasVP, Paluras"
  },
  {
    "name": "Mythic Seal #9",
    "description": "Unique NFT Mythical Seal for your Sunflower Land Farm. Made by Project Dignity.",
    "image": "https://raw.githubusercontent.com/tiffanydys/seals/main/preview/seal_preview.gif",
    "edition": 9,
    "date": 1659861041798,
    "founders": "Project Dignity: Tiffanydys, DonatasDee, VadimasVP, Paluras"
  }
]